science_synapse-2.2.0.dist-info/licenses/LICENSE
synapse/__init__.py
synapse/__init__.pyi
synapse/api/__init__.py
synapse/api/__init__.pyi
synapse/api/channel_pb2.py
synapse/api/datatype_pb2.py
synapse/api/files_pb2.py
synapse/api/logging_pb2.py
synapse/api/node_pb2.py
synapse/api/query_pb2.py
synapse/api/status_pb2.py
synapse/api/synapse_pb2.py
synapse/api/synapse_pb2_grpc.py
synapse/api/time_pb2.py
synapse/api/nodes/__init__.py
synapse/api/nodes/__init__.pyi
synapse/api/nodes/broadband_source_pb2.py
synapse/api/nodes/controller_pb2.py
synapse/api/nodes/disk_writer_pb2.py
synapse/api/nodes/electrical_stimulation_pb2.py
synapse/api/nodes/optical_stimulation_pb2.py
synapse/api/nodes/signal_config_pb2.py
synapse/api/nodes/signal_status_pb2.py
synapse/api/nodes/spectral_filter_pb2.py
synapse/api/nodes/spike_binner_pb2.py
synapse/api/nodes/spike_detect_pb2.py
synapse/api/nodes/spike_detector_pb2.py
synapse/api/nodes/spike_source_pb2.py
synapse/api/nodes/stream_in_pb2.py
synapse/api/nodes/stream_out_pb2.py
synapse/cli/__init__.py
synapse/cli/__init__.pyi
synapse/cli/__main__.py
synapse/cli/discover.py
synapse/cli/files.py
synapse/cli/offline_plot.py
synapse/cli/query.py
synapse/cli/rpc.py
synapse/cli/streaming.py
synapse/cli/synapse_plotter.py
synapse/client/__init__.py
synapse/client/__init__.pyi
synapse/client/channel.py
synapse/client/config.py
synapse/client/device.py
synapse/client/node.py
synapse/client/sftp.py
synapse/client/signal_config.py
synapse/client/nodes/__init__.py
synapse/client/nodes/__init__.pyi
synapse/client/nodes/broadband_source.py
synapse/client/nodes/disk_writer.py
synapse/client/nodes/electrical_stimulation.py
synapse/client/nodes/optical_stimulation.py
synapse/client/nodes/signal_config.py
synapse/client/nodes/spectral_filter.py
synapse/client/nodes/spike_binner.py
synapse/client/nodes/spike_detector.py
synapse/client/nodes/spike_source.py
synapse/client/nodes/stream_in.py
synapse/client/nodes/stream_out.py
synapse/examples/__init__.py
synapse/examples/__init__.pyi
science_synapse-2.2.0.dist-info/METADATA
science_synapse-2.2.0.dist-info/WHEEL
science_synapse-2.2.0.dist-info/entry_points.txt
science_synapse-2.2.0.dist-info/top_level.txt
science_synapse-2.2.0.dist-info/RECORD
