Metadata-Version: 2.4
Name: science-synapse
Version: 2.2.0
Summary: Client library and CLI for the Synapse API
Author: Science Team
Author-email: team@science.xyz
Requires-Python: >=3.9
License-File: LICENSE
Requires-Dist: coolname
Requires-Dist: grpcio-tools
Requires-Dist: protoletariat
Requires-Dist: numpy>=2.0.0
Requires-Dist: pyserial
Requires-Dist: scipy
Requires-Dist: crcmod
Requires-Dist: rich
Requires-Dist: pyqtgraph
Requires-Dist: pyqt5
Requires-Dist: pandas>=2.2.0
Requires-Dist: dearpygui
Requires-Dist: pyzmq
Requires-Dist: pyyaml
Requires-Dist: paramiko>=3.5.1
Dynamic: author
Dynamic: author-email
Dynamic: description
Dynamic: description-content-type
Dynamic: license-file
Dynamic: requires-dist
Dynamic: requires-python
Dynamic: summary
